pdmv_http_client-2.1.0.dist-info/licenses/LICENSE
rest/__init__.py
rest/_version.py
rest/applications/__init__.py
rest/applications/base.py
rest/applications/mcm/__init__.py
rest/applications/mcm/core.py
rest/applications/mcm/invalidate_request.py
rest/applications/mcm/resubmission.py
rest/applications/rereco/core.py
rest/applications/stats/core.py
rest/client/__init__.py
rest/client/session.py
rest/client/auth/__init__.py
rest/client/auth/auth_interface.py
rest/client/auth/handlers/__init__.py
rest/client/auth/handlers/oauth2_tokens.py
rest/client/auth/handlers/session_cookies.py
rest/utils/__init__.py
rest/utils/logger.py
rest/utils/miscellaneous.py
rest/utils/shell.py
pdmv_http_client-2.1.0.dist-info/METADATA
pdmv_http_client-2.1.0.dist-info/WHEEL
pdmv_http_client-2.1.0.dist-info/top_level.txt
pdmv_http_client-2.1.0.dist-info/RECORD
