Metadata-Version: 2.4
Name: pdmv-http-client
Version: 2.1.0
Summary: A HTTP client wrapper to handle authenticated requests to CERN internal applications
Maintainer-email: PdmV Service <pdmv.service@cern.ch>, PPD Technical Support <cms-PPD-technical-support@cern.ch>
License-Expression: MIT
Project-URL: Repository, https://gitlab.cern.ch/cms-ppd/technical-support/libraries/pdmv-http-client
Classifier: Programming Language :: Python :: 3.9
Classifier: Programming Language :: Python :: 3.10
Classifier: Programming Language :: Python :: 3.11
Classifier: Programming Language :: Python :: 3.12
Requires-Python: >=3.9
License-File: LICENSE
Requires-Dist: requests>=2.32.5
Dynamic: license-file
